{
  "229200": {
    "name": "KODEX 코스닥150",
    "qty": 1,
    "buy_price": 18430.0,
    "target_price": 19500.0,
    "bought_at": "2026-05-18 01:34:44",
    "ai_prediction": {
      "signal": "BUY",
      "confidence": 70,
      "target_price": 19500,
      "stop_loss": 18000,
      "reason": "RSI가 40.2로 낮고 볼린저밴드 하단 근처에 위치하여 강한 매수 신호를 나타냅니다. 외국인과 기관의 순매수가 지속되고 있어 긍정적인 수급 상황입니다."
    },
    "total_planned_qty": 1,
    "buy_count": 1,
    "highest_price": 18430.0,
    "trailing_stop": 17508.5
  },
  "305540": {
    "name": "TIGER 2차전지테마",
    "qty": 1,
    "buy_price": 23665.0,
    "target_price": 25000.0,
    "bought_at": "2026-05-18 01:34:59",
    "ai_prediction": {
      "signal": "BUY",
      "confidence": 65,
      "target_price": 25000,
      "stop_loss": 22000,
      "reason": "RSI가 44.58로 40 이하가 아니지만, 볼린저밴드 위치가 0.093으로 하단 근처에 있어 매수 관심이 높습니다. 외국인과 기관의 순매수가 지속되고 있어 긍정적인 수급 상황입니다."
    },
    "total_planned_qty": 1,
    "buy_count": 1,
    "highest_price": 23665.0,
    "trailing_stop": 22481.75
  }
}